python_boilerplate/__init__.py
python_boilerplate/cli.py
python_boilerplate/python_boilerplate.py
python_boilerplate_uwbobqpgbvbg-0.1.1.dist-info/AUTHORS.rst
python_boilerplate_uwbobqpgbvbg-0.1.1.dist-info/LICENSE
python_boilerplate_uwbobqpgbvbg-0.1.1.dist-info/METADATA
python_boilerplate_uwbobqpgbvbg-0.1.1.dist-info/WHEEL
python_boilerplate_uwbobqpgbvbg-0.1.1.dist-info/entry_points.txt
python_boilerplate_uwbobqpgbvbg-0.1.1.dist-info/top_level.txt
python_boilerplate_uwbobqpgbvbg-0.1.1.dist-info/RECORD
