Metadata-Version: 2.1
Name: python-boilerplate-uwbobqpgbvbg
Version: 0.1.1
Summary: Python Boilerplate contains all the boilerplate you need to create a Python package.
Home-page: https://github.com/Lothiraldan/python_boilerplate
Author: Boris Feld
Author-email: lothiraldan@gmail.com
License: GNU General Public License v3
Keywords: python_boilerplate
Platform: UNKNOWN
Classifier: Development Status :: 2 - Pre-Alpha
Classifier: Intended Audience :: Developers
Classifier: License :: OSI Approved :: GNU General Public License v3 (GPLv3)
Classifier: Natural Language :: English
Classifier: Programming Language :: Python :: 2
Classifier: Programming Language :: Python :: 2.7
Classifier: Programming Language :: Python :: 3
Classifier: Programming Language :: Python :: 3.5
Classifier: Programming Language :: Python :: 3.6
Classifier: Programming Language :: Python :: 3.7
Requires-Python: >=2.7, !=3.0.*, !=3.1.*, !=3.2.*, !=3.3.*, !=3.4.*
Requires-Dist: Click (>=7.0)
